{
  "$schema": "https://developer.microsoft.com/json-schemas/fabric/item/report/definition/visualContainer/2.10.0/schema.json",
  "name": "9c6c62f5a46e18698cb1",
  "position": {
    "x": 242.88246034271933,
    "y": 0,
    "z": 2000,
    "height": 120.75512152632373,
    "width": 201.7159416405635,
    "tabOrder": 2000
  },
  "visual": {
    "visualType": "cardVisual",
    "query": {
      "queryState": {
        "Data": {
          "projections": [
            {
              "field": {
                "Aggregation": {
                  "Expression": {
                    "Column": {
                      "Expression": {
                        "SourceRef": {
                          "Entity": "public games"
                        }
                      },
                      "Property": "title"
                    }
                  },
                  "Function": 2
                }
              },
              "queryRef": "Min(public games.title)",
              "nativeQueryRef": "Contagem de title"
            }
          ]
        }
      },
      "sortDefinition": {
        "sort": [
          {
            "field": {
              "Aggregation": {
                "Expression": {
                  "Column": {
                    "Expression": {
                      "SourceRef": {
                        "Entity": "public games"
                      }
                    },
                    "Property": "title"
                  }
                },
                "Function": 2
              }
            },
            "direction": "Descending"
          }
        ],
        "isDefaultSort": true
      }
    },
    "visualContainerObjects": {
      "title": [
        {
          "properties": {
            "show": {
              "expr": {
                "Literal": {
                  "Value": "true"
                }
              }
            },
            "text": {
              "expr": {
                "Literal": {
                  "Value": "'Total Games'"
                }
              }
            }
          }
        }
      ]
    },
    "drillFilterOtherVisuals": true
  },
  "filterConfig": {
    "filters": [
      {
        "name": "23f748f80436c973eabe",
        "field": {
          "Aggregation": {
            "Expression": {
              "Column": {
                "Expression": {
                  "SourceRef": {
                    "Entity": "public games"
                  }
                },
                "Property": "title"
              }
            },
            "Function": 2
          }
        },
        "type": "Advanced"
      }
    ]
  }
}