{
  "$schema": "https://developer.microsoft.com/json-schemas/fabric/item/report/definition/visualContainer/2.10.0/schema.json",
  "name": "66e13d8da95c0e516fe1",
  "position": {
    "x": 898.80232499706869,
    "y": 0,
    "z": 5000,
    "height": 270.32680614415654,
    "width": 381.47640663997726,
    "tabOrder": 5000
  },
  "visual": {
    "visualType": "lineChart",
    "query": {
      "queryState": {
        "Category": {
          "projections": [
            {
              "field": {
                "Column": {
                  "Expression": {
                    "SourceRef": {
                      "Entity": "DimDate"
                    }
                  },
                  "Property": "Year"
                }
              },
              "queryRef": "DimDate.Year",
              "nativeQueryRef": "Year",
              "active": true
            }
          ]
        },
        "Y": {
          "projections": [
            {
              "field": {
                "Aggregation": {
                  "Expression": {
                    "Column": {
                      "Expression": {
                        "SourceRef": {
                          "Entity": "public sales"
                        }
                      },
                      "Property": "revenue_usd"
                    }
                  },
                  "Function": 0
                }
              },
              "queryRef": "Sum(public sales.revenue_usd)",
              "nativeQueryRef": "Soma de revenue_usd"
            }
          ]
        }
      },
      "sortDefinition": {
        "sort": [
          {
            "field": {
              "Aggregation": {
                "Expression": {
                  "Column": {
                    "Expression": {
                      "SourceRef": {
                        "Entity": "public sales"
                      }
                    },
                    "Property": "revenue_usd"
                  }
                },
                "Function": 0
              }
            },
            "direction": "Descending"
          }
        ],
        "isDefaultSort": true
      }
    },
    "visualContainerObjects": {
      "title": [
        {
          "properties": {
            "text": {
              "expr": {
                "Literal": {
                  "Value": "'Annual Revenue'"
                }
              }
            }
          }
        }
      ]
    },
    "drillFilterOtherVisuals": true
  },
  "filterConfig": {
    "filters": [
      {
        "name": "4d0190251c6bbc7e65c1",
        "field": {
          "Column": {
            "Expression": {
              "SourceRef": {
                "Entity": "public sales"
              }
            },
            "Property": "sale_date"
          }
        },
        "type": "Categorical",
        "howCreated": "User"
      },
      {
        "name": "834993d9a8c07bfe604a",
        "field": {
          "Column": {
            "Expression": {
              "SourceRef": {
                "Entity": "public sales"
              }
            },
            "Property": "sale_date"
          }
        },
        "type": "Categorical",
        "howCreated": "User"
      },
      {
        "name": "bb8271866e99c5b558ce",
        "field": {
          "Column": {
            "Expression": {
              "SourceRef": {
                "Entity": "public sales"
              }
            },
            "Property": "sale_date"
          }
        },
        "type": "Advanced",
        "howCreated": "User"
      },
      {
        "name": "94cfd4b82540faf21bab",
        "field": {
          "Aggregation": {
            "Expression": {
              "Column": {
                "Expression": {
                  "SourceRef": {
                    "Entity": "public sales"
                  }
                },
                "Property": "revenue_usd"
              }
            },
            "Function": 0
          }
        },
        "type": "Advanced"
      },
      {
        "name": "fe029fa4fb737fc8c2d8",
        "field": {
          "Column": {
            "Expression": {
              "SourceRef": {
                "Entity": "DimDate"
              }
            },
            "Property": "Year"
          }
        },
        "type": "Advanced"
      }
    ]
  }
}